dbugging/__init__.py
dbugging/decorators.py
dbugging-0.0.1a3.dist-info/LICENSE.txt
dbugging-0.0.1a3.dist-info/METADATA
dbugging-0.0.1a3.dist-info/WHEEL
dbugging-0.0.1a3.dist-info/entry_points.txt
dbugging-0.0.1a3.dist-info/top_level.txt
dbugging-0.0.1a3.dist-info/RECORD
